catchMinor/VERSION
catchMinor/__init__.py
catchMinor/base/__init__.py
catchMinor/base/base_config.py
catchMinor/base/base_lit_model.py
catchMinor/base/base_torch_model.py
catchMinor/data_load/__init__.py
catchMinor/data_load/dataset.py
catchMinor/stat_model/__init__.py
catchMinor/tabular_model/__init__.py
catchMinor/tabular_model/AutoEncoder/__init__.py
catchMinor/tabular_model/AutoEncoder/ae_config.py
catchMinor/tabular_model/AutoEncoder/lit_ae.py
catchMinor/tabular_model/AutoEncoder/torch_ae.py
catchMinor/time_series_model/__init__.py
catchMinor/utils/__init__.py
catchMinor/utils/data.py
catchMinor/utils/debug.py
test/__init__.py
catchMinor-0.0.1.dist-info/LICENSE
catchMinor-0.0.1.dist-info/METADATA
catchMinor-0.0.1.dist-info/WHEEL
catchMinor-0.0.1.dist-info/top_level.txt
catchMinor-0.0.1.dist-info/RECORD
