Metadata-Version: 2.1
Name: catchMinor
Version: 0.0.1
Summary: model library for imbalanced-learning & anomaly detection in tabular, time series, graph data
Home-page: https://github.com/minsoo9506/catchMinor
Author: minsoo9506
Author-email: ghktjd15gh@gmail.com
License: MIT
Requires-Python: ==3.10
License-File: LICENSE
Requires-Dist: aiohttp ==3.8.3
Requires-Dist: black ==22.12.0
Requires-Dist: flake8 ==6.0.0
Requires-Dist: fqdn ==1.5.1
Requires-Dist: isoduration ==20.11.0
Requires-Dist: isort ==5.11.4
Requires-Dist: jsonpointer ==2.3
Requires-Dist: jupyter ==1.0.0
Requires-Dist: lightning ==2.0.1.post0
Requires-Dist: mypy ==0.991
Requires-Dist: pandas ==1.5.3
Requires-Dist: path ==16.6.0
Requires-Dist: pip-chill ==1.0.1
Requires-Dist: pre-commit ==2.21.0
Requires-Dist: scikit-learn ==1.2.1
Requires-Dist: tensorboard ==2.12.2
Requires-Dist: torchaudio ==0.13.1
Requires-Dist: torchvision ==0.14.1
Requires-Dist: uri-template ==1.2.0
Requires-Dist: webcolors ==1.12
